tyron
