Metadata-Version: 1.0
Name: tyron
Version: 0.2.4
Summary: Gevent redis/pubsub event notifier written in flask and gevent
Home-page: https://github.com/tbarbugli/tyron
Author: Tommaso Barbugli
Author-email: tbarbugli@gmail.com
License: BSD
Platform: OS Independent
Classifier: Development Status :: 4 - Beta
Classifier: Framework :: Django
Classifier: Intended Audience :: Developers
Classifier: License :: OSI Approved :: BSD License
Classifier: Operating System :: OS Independent
Classifier: Programming Language :: Python
Classifier: Programming Language :: Python :: 2.7
Classifier: Topic :: Internet :: WWW/HTTP
